coresite/__init__.py
coresite/asgi.py
coresite/settings.py
coresite/urls.py
coresite/wsgi.py
corunaApp/__init__.py
corunaApp/admin.py
corunaApp/apps.py
corunaApp/forms.py
corunaApp/models.py
corunaApp/tests.py
corunaApp/urls.py
corunaApp/views.py
corunaApp/migrations/0001_initial.py
corunaApp/migrations/0002_auto_20200402_2004.py
corunaApp/migrations/0003_auto_20200402_2234.py
corunaApp/migrations/0004_auto_20200402_2329.py
corunaApp/migrations/0005_auto_20200405_1404.py
corunaApp/migrations/__init__.py
pkg_avinashnishad-0.0.1.dist-info/METADATA
pkg_avinashnishad-0.0.1.dist-info/WHEEL
pkg_avinashnishad-0.0.1.dist-info/top_level.txt
pkg_avinashnishad-0.0.1.dist-info/RECORD
