Metadata-Version: 2.1
Name: pkg-avinashnishad
Version: 0.0.1
Summary: A small example package
Home-page: https://github.com/jsavinash/coronac
Author: Avinash Nishad
Author-email: js.avinash.nishad@gmail.com
License: UNKNOWN
Platform: UNKNOWN
Classifier: Programming Language :: Python :: 3
Classifier: License :: OSI Approved :: MIT License
Classifier: Operating System :: OS Independent
Requires-Python: >=3.8
